{
  "config": {
    "mapName": "c1-f1"
  },
  "items": {
    "c1-f1-n108": {
      "id": "c1-f1-n108",
      "name": "Название 1",
      "action": "auditory",
      "disc": "Описание 1",
      "subdivision": "ФИСТ",
      "timetableLink": "https://time.ulstu.ru/timetable?filter=%D0%9F%D0%98%D0%B1%D0%B4-11",
      "capacity": 30,
      "additional": ""
    },
    "c1-f1-n123": {
      "id": "c1-f1-n123",
      "name": "Название 1",
      "action": "auditory",
      "disc": "Описание 1"
    },
    "c1-f1-n119": {
      "id": "c1-f1-n119",
      "name": "Название 1",
      "action": "auditory",
      "disc": "Описание 1"
    },
    "c1-f1-n119a": {
      "id": "c1-f1-n119a",
      "name": "Название 1",
      "action": "auditory",
      "disc": "Описание 1"
    },
    "c1-f1-n104": {
      "id": "c1-f1-n104",
      "name": "Название 1",
      "action": "auditory",
      "disc": "Описание 1"
    },
    "c1-f1-n115": {
      "id": "c1-f1-n115",
      "name": "Название 1",
      "action": "auditory",
      "disc": "Описание 1"
    },
    "c1-f1-n113": {
      "id": "c1-f1-n113",
      "name": "Название 1",
      "action": "auditory",
      "disc": "Описание 1"
    },
    "c1-f1-n109": {
      "id": "c1-f1-n109",
      "name": "Название 1",
      "action": "auditory",
      "disc": "Описание 1"
    },
    "c1-f1-n107": {
      "id": "c1-f1-n107",
      "name": "Название 1",
      "action": "auditory",
      "disc": "Описание 1"
    },
    "c1-f1-n102": {
      "id": "c1-f1-n102",
      "name": "Название 1",
      "action": "auditory",
      "disc": "Описание 1"
    },
    "c1-f1-n105": {
      "id": "c1-f1-n105",
      "name": "Название 1",
      "action": "auditory",
      "disc": "Описание 1"
    },
    "c1-f1-n101": {
      "id": "c1-f1-n101",
      "name": "Название 1",
      "action": "auditory",
      "disc": "Описание 1"
    },
    "c1-f1-n99": {
      "id": "c1-f1-n99",
      "name": "Название 1",
      "action": "auditory",
      "disc": "Описание 1"
    },
    "c1-f1-wc": {
      "id": "c1-f1-wc",
      "name": "Название 1",
      "action": "auditory",
      "disc": "Описание 1"
    },
    "c1-f1-n91": {
      "id": "c1-f1-n91",
      "name": "Название 1",
      "action": "auditory",
      "disc": "Описание 1"
    },
    "c1-f1-n92": {
      "id": "c1-f1-n92",
      "name": "Название 1",
      "action": "auditory",
      "disc": "Описание 1"
    },
    "c1-f1-n93": {
      "id": "c1-f1-n93",
      "name": "Название 1",
      "action": "auditory",
      "disc": "Описание 1"
    },
    "c1-f1-n94": {
      "id": "c1-f1-n94",
      "name": "Название 1",
      "action": "auditory",
      "disc": "Описание 1"
    },
    "c1-f1-n96": {
      "id": "c1-f1-n96",
      "name": "Название 1",
      "action": "auditory",
      "disc": "Описание 1"
    },
    "c1-f1-n95": {
      "id": "c1-f1-n95",
      "name": "Название 1",
      "action": "auditory",
      "disc": "Описание 1"
    },
    "c1-f1-n103": {
      "id": "c1-f1-n103",
      "name": "Название 1",
      "action": "auditory",
      "disc": "Описание 1"
    },
    "c1-f1-n100": {
      "id": "c1-f1-n100",
      "name": "Название 1",
      "action": "auditory",
      "disc": "Описание 1"
    },
    "c1-f1-n97": {
      "id": "c1-f1-n97",
      "name": "Название 1",
      "action": "auditory",
      "disc": "Описание 1"
    },
    "c1-f1-n119a_2": {
      "id": "c1-f1-n119a_2",
      "name": "Название 1",
      "action": "auditory",
      "disc": "Описание 1"
    },
    "c1-f1-cloakroom": {
      "id": "c1-f1-cloakroom",
      "name": "Название 1",
      "action": "auditory",
      "disc": "Описание 1"
    },
    "c1-f1-security": {
      "id": "c1-f1-security",
      "name": "Название 1",
      "action": "auditory",
      "disc": "Описание 1"
    },
    "c1-f1-n119a_3": {
      "id": "c1-f1-n119a_3",
      "name": "Название 1",
      "action": "auditory",
      "disc": "Описание 1"
    },
    "c1-f1-n119a_4": {
      "id": "c1-f1-n119a_4",
      "name": "Название 1",
      "action": "auditory",
      "disc": "Описание 1"
    },
    "c1-f1-n127": {
      "id": "c1-f1-n127",
      "name": "Название 1",
      "action": "auditory",
      "disc": "Описание 1"
    },
    "c1-f1-n125": {
      "id": "c1-f1-n125",
      "name": "Название 1",
      "action": "auditory",
      "disc": "Описание 1"
    },
    "c1-f1-n134": {
      "id": "c1-f1-n134",
      "name": "Название 1",
      "action": "auditory",
      "disc": "Описание 1"
    },
    "c1-f1-n129": {
      "id": "c1-f1-n129",
      "name": "Название 1",
      "action": "auditory",
      "disc": "Описание 1"
    },
    "c1-f1-n130": {
      "id": "c1-f1-n130",
      "name": "Название 1",
      "action": "auditory",
      "disc": "Описание 1"
    },
    "c1-f1-n133": {
      "id": "c1-f1-n133",
      "name": "Название 1",
      "action": "auditory",
      "disc": "Описание 1"
    },
    "c1-f1-n135": {
      "id": "c1-f1-n135",
      "name": "Название 1",
      "action": "auditory",
      "disc": "Описание 1"
    },
    "c1-f1-n131": {
      "id": "c1-f1-n131",
      "name": "Название 1",
      "action": "auditory",
      "disc": "Описание 1"
    },
    "c1-f1-n140a": {
      "id": "c1-f1-n140a",
      "name": "Название 1",
      "action": "auditory",
      "disc": "Описание 1"
    },
    "c1-f1-n120": {
      "id": "c1-f1-n120",
      "name": "Название 1",
      "action": "auditory",
      "disc": "Описание 1"
    },
    "c1-f1-n132": {
      "id": "c1-f1-n132",
      "name": "Название 1",
      "action": "auditory",
      "disc": "Описание 1"
    },
    "c1-f1-n134a": {
      "id": "c1-f1-n134a",
      "name": "Название 1",
      "action": "auditory",
      "disc": "Описание 1"
    },
    "c1-f1-n140b": {
      "id": "c1-f1-n140b",
      "name": "Название 1",
      "action": "auditory",
      "disc": "Описание 1"
    },
    "c1-f1-n136": {
      "id": "c1-f1-n136",
      "name": "Название 1",
      "action": "auditory",
      "disc": "Описание 1"
    },
    "c1-f1-n112": {
      "id": "c1-f1-n112",
      "name": "Название 1",
      "action": "auditory",
      "disc": "Описание 1"
    },
    "c1-f1-n111": {
      "id": "c1-f1-n111",
      "name": "Название 1",
      "action": "auditory",
      "disc": "Описание 1"
    },
    "c1-f1-n136a": {
      "id": "c1-f1-n136a",
      "name": "Название 1",
      "action": "auditory",
      "disc": "Описание 1"
    },
    "c1-f1-n114": {
      "id": "c1-f1-n114",
      "name": "Название 1",
      "action": "auditory",
      "disc": "Описание 1"
    },
    "c1-f1-n116": {
      "id": "c1-f1-n116",
      "name": "Название 1",
      "action": "auditory",
      "disc": "Описание 1"
    },
    "c1-f1-n118": {
      "id": "c1-f1-n118",
      "name": "Название 1",
      "action": "auditory",
      "disc": "Описание 1"
    },
    "stairs": {
      "id": "stairs_1",
      "name": "Название 1",
      "action": "move",
      "direction": "global",
      "directionName": "Общая карта",
      "disc": "Описание 1"
    },
    "stairs_2": {
      "id": "stairs_2",
      "name": "Название 1",
      "action": "move",
      "direction": "global",
      "directionName": "Общая карта",
      "disc": "Описание 1"
    },
    "stairs_3": {
      "id": "stairs_3",
      "name": "Название 1",
      "action": "move",
      "direction": "global",
      "directionName": "Общая карта",
      "disc": "Описание 1"
    },
    "stairs_4": {
      "id": "stairs_4",
      "name": "Название 1",
      "action": "move",
      "direction": "global",
      "directionName": "Общая карта",
      "disc": "Описание 1"
    },
    "stairs_5": {
      "id": "stairs_5",
      "name": "Название 1",
      "action": "move",
      "direction": "global",
      "directionName": "Общая карта",
      "disc": "Описание 1"
    }
  }
}